cntdrun.py
cntdrun-1.0.5.dist-info/METADATA
cntdrun-1.0.5.dist-info/WHEEL
cntdrun-1.0.5.dist-info/entry_points.txt
cntdrun-1.0.5.dist-info/top_level.txt
cntdrun-1.0.5.dist-info/RECORD
