Metadata-Version: 2.1
Name: cntdrun
Version: 1.0.5
Summary: A countdown running program tool
Author: gzj
Author-email: gzj00@outlook.com
Requires-Dist: pyqt5
